<?xml version="1.0"?>
<config version="1.3">
	<databases>
		<database>
			<database_config_file></database_config_file><!-- pre set -->
			<read_from_config>n</read_from_config>
			<host>localhost</host> <!-- localhost -->
			<username></username> <!-- root -->
			<password></password>
			<dbname></dbname>
		</database>
	</databases>

	<archive>
		<type>git</type>
		<git>
			<repo></repo> <!-- git@github.com:nedstars/Deploy-Script.git -->
			<branch></branch>
			<source_folder></source_folder> <!-- web -->
		</git>
	</archive>

	<notifications>
		<email_addresses>
			<address></address>
		</email_addresses>
		<!-- <pushover_users>
			<user></user>
		</pushover_users> -->
	</notifications>

	<paths>
		<web_live_path></web_live_path>
		<temp_new_path></temp_new_path> <!-- /staging.new.tmp -->
		<temp_old_path></temp_old_path> <!-- /staging.old.tmp -->
	</paths>
	<backup>
		<folder></folder>
		<retention_days>30</retention_days> <!-- 30 -->
		<make_database_backup>y</make_database_backup><!-- y or n-->
		<make_file_backup>y</make_file_backup><!-- y or n-->
	</backup>

	<preserve_data>
		<folders> <!-- pre set -->
			<folder>wp-content/uploads</folder>

			<!--
			UNCOMMENT the following line if users are able to install plugins from the
			backend interface, meaning they are not under version control
			-->
			<!--<folder>wp-content/plugins</folder>-->

			<!--
			UNCOMMENT the following line if users are able to install themes from the
			backend interface, meaning they are not under version control
			-->
			<!--<folder>wp-content/themes</folder>-->
		</folders>
		<files> <!-- pre set -->
			<file>sitemap.xml</file><!-- generated by numerous SEO plugins, including WordPress SEO by Yoast -->
			<file>sitemap.xml.gz</file><!-- generated by numerous SEO plugins, including WordPress SEO by Yoast -->
			<file>wp-config.php</file>
		</files>
		<google_files>y</google_files><!-- pre set -->
	</preserve_data>

	<permisions>
		<user>apache</user> <!-- pre set -->
		<group>apache</group> <!-- pre set -->
	</permisions>
</config>
